{
  "main": {
    "id": "e697584dcd0dc51a",
    "type": "split",
    "children": [
      {
        "id": "da6d26faca5fe605",
        "type": "tabs",
        "children": [
          {
            "id": "2ba8306456108f48",
            "type": "leaf",
            "state": {
              "type": "markdown",
              "state": {
                "file": "02_项目笔记/03_拖把数藏/04_业务功能.md",
                "mode": "source",
                "source": false
              },
              "icon": "lucide-file",
              "title": "04_业务功能"
            }
          },
          {
            "id": "ca0ebbe9af38c072",
            "type": "leaf",
            "state": {
              "type": "markdown",
              "state": {
                "file": "02_项目笔记/03_拖把数藏/03_最佳实践.md",
                "mode": "source",
                "source": false
              },
              "icon": "lucide-file",
              "title": "03_最佳实践"
            }
          },
          {
            "id": "79e7b1d64893f1a9",
            "type": "leaf",
            "state": {
              "type": "markdown",
              "state": {
                "file": "03_八股文/04_Redis八股.md",
                "mode": "source",
                "source": false
              },
              "icon": "lucide-file",
              "title": "04_Redis八股"
            }
          }
        ],
        "currentTab": 2
      }
    ],
    "direction": "vertical"
  },
  "left": {
    "id": "45549a84d611ecdc",
    "type": "split",
    "children": [
      {
        "id": "9e7b55bedb147ee5",
        "type": "tabs",
        "children": [
          {
            "id": "5c2c5105078021e7",
            "type": "leaf",
            "state": {
              "type": "file-explorer",
              "state": {
                "sortOrder": "alphabetical",
                "autoReveal": false
              },
              "icon": "lucide-folder-closed",
              "title": "文件列表"
            }
          },
          {
            "id": "929a8fdae625b599",
            "type": "leaf",
            "state": {
              "type": "search",
              "state": {
                "query": "最长递增子序列",
                "matchingCase": false,
                "explainSearch": false,
                "collapseAll": false,
                "extraContext": false,
                "sortOrder": "alphabetical"
              },
              "icon": "lucide-search",
              "title": "搜索"
            }
          },
          {
            "id": "fc845e5391f7d965",
            "type": "leaf",
            "state": {
              "type": "bookmarks",
              "state": {},
              "icon": "lucide-bookmark",
              "title": "书签"
            }
          },
          {
            "id": "fe1161c9466568fe",
            "type": "leaf",
            "state": {
              "type": "tag",
              "state": {
                "sortOrder": "alphabetical",
                "useHierarchy": false
              },
              "icon": "lucide-tags",
              "title": "标签"
            }
          }
        ]
      }
    ],
    "direction": "horizontal",
    "width": 285.5,
    "collapsed": true
  },
  "right": {
    "id": "45beac71d173d048",
    "type": "split",
    "children": [
      {
        "id": "528ef4cb0897dff7",
        "type": "tabs",
        "children": [
          {
            "id": "7f9bd1c5f9f9f687",
            "type": "leaf",
            "state": {
              "type": "git-view",
              "state": {},
              "icon": "git-pull-request",
              "title": "Source Control"
            }
          },
          {
            "id": "f25c1712022f3014",
            "type": "leaf",
            "state": {
              "type": "calendar",
              "state": {},
              "icon": "calendar-with-checkmark",
              "title": "Calendar"
            }
          },
          {
            "id": "81b75f44518705b1",
            "type": "leaf",
            "state": {
              "type": "quiet-outline",
              "state": {},
              "icon": "lines-of-text",
              "title": "Quiet Outline"
            }
          }
        ],
        "currentTab": 2
      }
    ],
    "direction": "horizontal",
    "width": 320.5,
    "collapsed": true
  },
  "left-ribbon": {
    "hiddenItems": {
      "switcher:打开快速切换": false,
      "graph:查看关系图谱": false,
      "canvas:新建白板": false,
      "daily-notes:打开/创建今天的日记": false,
      "templates:插入模板": false,
      "command-palette:打开命令面板": false,
      "remotely-save:Remotely Save": false,
      "random-note:开始漫游笔记": false,
      "markdown-importer:打开 Markdown 格式转换器": false,
      "table-editor-obsidian:Advanced Tables Toolbar": false
    }
  },
  "active": "79e7b1d64893f1a9",
  "lastOpenFiles": [
    "02_项目笔记/03_拖把数藏/04_业务功能.md",
    "02_项目笔记/03_拖把数藏/03_最佳实践.md",
    "05_力扣刷题笔记/07_动态规划.md",
    "05_力扣刷题笔记/02_链表.md",
    "99999_暂未分类_文章/缓存与数据库的一致性方案总结及代码demo.md",
    "99999_暂未分类_文章/imgs/Pasted image 20250301003948.png",
    "99999_暂未分类_文章/imgs/Pasted image 20250301001607.png",
    "99999_暂未分类_文章/imgs/Pasted image 20250301000946.png",
    "99999_暂未分类_文章/imgs/Pasted image 20250228174823.png",
    "99999_暂未分类_文章/imgs/Pasted image 20250228174728.png",
    "100_面试记录/面试记录.md",
    "03_八股文/04_Redis八股.md",
    "99999_暂未分类_文章/imgs/Pasted image 20250228172450.png",
    "99999_暂未分类_文章/imgs",
    "03_八股文/03_MySQL八股.md",
    "03_八股文/imgs/Pasted image 20250228143914.png",
    "Obsidian使用指南.md",
    "05_力扣刷题笔记/04_哈希表.md",
    "05_力扣刷题笔记/09_单调栈.md",
    "05_力扣刷题笔记/06_栈与队列.md",
    "05_力扣刷题笔记/06_贪心算法.md",
    "05_力扣刷题笔记/刷题笔记.md",
    "03_八股文/05_JUC八股.md",
    "05_力扣刷题笔记/03_字符串.md",
    "02_项目笔记/99_牛券/开发日志.md",
    "99999_暂未分类_文章",
    "05_力扣刷题笔记/01_数组.md",
    "02_项目笔记/03_拖把数藏/imgs/Pasted image 20250224002153.png",
    "02_项目笔记/03_拖把数藏/imgs/Pasted image 20250224001721.png",
    "05_力扣刷题笔记/11_回溯.md",
    "02_项目笔记/03_拖把数藏/imgs/Pasted image 20250223022843.png",
    "02_项目笔记/03_拖把数藏/05_重构逻辑.md",
    "05_力扣刷题笔记/05_二叉树.md",
    "04_场景题/场景题总结.md",
    "03_八股文/02_Spring八股文.md",
    "99_每日学习记录/学习记录_0219-0223.md",
    "05_力扣刷题笔记/08_图论.md",
    "架构设计思想",
    "01_课程学习笔记/未命名",
    "01_课程学习笔记/设计模式/imgs",
    "01_课程学习笔记/设计模式",
    "02_项目笔记/04_动态线程池",
    "100_面试记录",
    "02_项目笔记/03_拖把数藏/imgs",
    "02_项目笔记/03_拖把数藏",
    "八股文/未命名.canvas"
  ]
}